pi_vae_pytorch/__init__.py
pi_vae_pytorch/decoders.py
pi_vae_pytorch/encoders.py
pi_vae_pytorch/label_prior.py
pi_vae_pytorch/layers.py
pi_vae_pytorch/loss.py
pi_vae_pytorch/pivae.py
pi_vae_pytorch-1.1.0.dist-info/LICENSE
pi_vae_pytorch-1.1.0.dist-info/METADATA
pi_vae_pytorch-1.1.0.dist-info/WHEEL
pi_vae_pytorch-1.1.0.dist-info/top_level.txt
pi_vae_pytorch-1.1.0.dist-info/RECORD
