Metadata-Version: 2.2
Name: pi-vae-pytorch
Version: 1.1.0
Summary: A Pytorch implementation of Poisson Identifiable VAE (pi-VAE), a variational auto encoder used to construct latent variable models of neural activity while simultaneously modeling the relation between the latent and task variables.
Author-email: Marlan McInnes-Taylor <mmcinnestaylor@gmail.com>
Maintainer-email: Marlan McInnes-Taylor <mmcinnestaylor@gmail.com>
Project-URL: Homepage, https://github.com/mmcinnestaylor/pi-vae-pytorch
Project-URL: Documentation, https://mmcinnestaylor.github.io/pi-vae-pytorch/
Project-URL: Download, https://github.com/mmcinnestaylor/pi-vae-pytorch/tags
Project-URL: Repository, https://github.com/mmcinnestaylor/pi-vae-pytorch.git
Project-URL: Issues, https://github.com/mmcinnestaylor/pi-vae-pytorch/issues
Keywords: artificial intelligence,deep learning,vae,variational autoencoder,pi-vae,poisson identifiable vae,poisson identifiable variational autoencoder,identifiable vae,identifiable variational autoencoder
Classifier: Development Status :: 5 - Production/Stable
Classifier: Intended Audience :: Developers
Classifier: Intended Audience :: Science/Research
Classifier: License :: OSI Approved :: MIT License
Classifier: Programming Language :: Python :: 3
Classifier: Programming Language :: Python :: 3.9
Classifier: Programming Language :: Python :: 3.10
Classifier: Programming Language :: Python :: 3.11
Classifier: Programming Language :: Python :: 3.12
Classifier: Topic :: Scientific/Engineering :: Artificial Intelligence
Classifier: Topic :: Scientific/Engineering :: Information Analysis
Requires-Python: >=3.9
License-File: LICENSE
Requires-Dist: torch>=2.0
